macaw/__init__.py
macaw/generators.py
macaw/macaw.py
macaw/version.py
macaw_py-1.0.1.dist-info/METADATA
macaw_py-1.0.1.dist-info/WHEEL
macaw_py-1.0.1.dist-info/top_level.txt
macaw_py-1.0.1.dist-info/RECORD
