Metadata-Version: 2.1
Name: macaw-py
Version: 1.0.1
Summary: MACAW molecular embedder and generator
Home-page: https://github.com/LBLQMM/macaw
Author: Vincent Blay
Author-email: vblayroger@lbl.gov
License: UNKNOWN
Keywords: cheminformatics,molecular design,drug discovery,synthetic biology
Platform: UNKNOWN
Classifier: Programming Language :: Python :: 3
Classifier: Programming Language :: Python :: 3.5
Classifier: Programming Language :: Python :: 3.6
Classifier: Programming Language :: Python :: 3.7
Classifier: Programming Language :: Python :: 3.8
Classifier: Programming Language :: Python :: 3 :: Only
Classifier: Operating System :: OS Independent
Classifier: Topic :: Scientific/Engineering :: Chemistry
Classifier: Intended Audience :: Science/Research
Classifier: Natural Language :: English
Requires-Dist: numpy (>=1.8.0)
Requires-Dist: scikit-learn (>=0.24.1)
Requires-Dist: scipy (>=1.6.1)
Requires-Dist: selfies (>=2.0.0)
Requires-Dist: umap-learn (>=0.5.2)
